NielsenDSRS/__init__.py
NielsenDSRS/module.py
NielsenRetail-0.1.2.dist-info/LICENSE
NielsenRetail-0.1.2.dist-info/METADATA
NielsenRetail-0.1.2.dist-info/WHEEL
NielsenRetail-0.1.2.dist-info/top_level.txt
NielsenRetail-0.1.2.dist-info/RECORD
