Metadata-Version: 2.1
Name: NielsenRetail
Version: 0.1.2
Summary: Nielsen Reader’s main purpose is to facilitate ease of processing of Nielsen Retail Scanner data...
Home-page: https://github.com/pratikrelekar/NielsenDSRS
Author: Pratik Relekar, Hrishikesh Relekar, Matias Carrasco Kind
Author-email: relekar2@illinois.edu, hrishkesh.relekar@chicagobooth.edu, mcarras2@illinois.edu
Classifier: Programming Language :: Python :: 3
Classifier: License :: OSI Approved :: MIT License
Classifier: Operating System :: OS Independent
Requires-Python: >=3.6
License-File: LICENSE
Requires-Dist: dask[dataframe] ==2024.8.0
Requires-Dist: distributed ==2024.8.0
Requires-Dist: numpy ==2.0.1
Requires-Dist: pandas ==2.2.2
Requires-Dist: toolz ==0.12.1
